clo/__init__.py
clo/__main__.py
clo/api.py
clo/input.py
clo/meta.py
clo/output.py
clo/types.py
clo-0.6.0.dist-info/LICENSE
clo-0.6.0.dist-info/METADATA
clo-0.6.0.dist-info/WHEEL
clo-0.6.0.dist-info/entry_points.txt
clo-0.6.0.dist-info/top_level.txt
clo-0.6.0.dist-info/RECORD
