Metadata-Version: 2.1
Name: clo
Version: 0.6.0
Summary: CLO (Command-Line Odoo) - Perform API operations on Odoo instances from the command-line.
Home-page: https://leshaunj.github.io/clo
Author: Arian Johnson
Author-email: i.am@ajohn.dev
License: GPLv3
Keywords: cli python3 odoo command-line-tool api xmlrpc
Classifier: Development Status :: 5 - Production/Stable
Classifier: Environment :: Web Environment
Classifier: Intended Audience :: Developers
Classifier: License :: OSI Approved :: GNU General Public License v3 (GPLv3)
Classifier: Natural Language :: English
Classifier: Operating System :: OS Independent
Classifier: Programming Language :: Python :: 3
Classifier: Programming Language :: Python :: 3.10
Classifier: Programming Language :: Python :: 3.11
Classifier: Programming Language :: Python :: 3.12
Classifier: Topic :: Utilities
Classifier: Typing :: Typed
Requires-Python: >=3.10
License-File: LICENSE
Requires-Dist: python-dotenv
Requires-Dist: requests
